fstk/Dialogs.py
fstk/Fstk.py
fstk/Globals.py
fstk/Palette.py
fstk/Redmine.py
fstk/SaveFiles.py
fstk/SavefilesMigrations.py
fstk/Updater.py
fstk/Utils.py
fstk/__init__.py
fstk/__main__.py
fstk/assets/Font Awesome 5 Pro-Light-300.otf
fstk/assets/__init__.py
fstk/assets/fast-switch-time-keeper.desktop
fstk/assets/icon.png
fstk-0.10.0.dist-info/METADATA
fstk-0.10.0.dist-info/WHEEL
fstk-0.10.0.dist-info/top_level.txt
fstk-0.10.0.dist-info/RECORD
