Metadata-Version: 2.4
Name: fstk
Version: 0.10.0
Summary: Fast Switch Time Keeper
Author: Meow
Classifier: Programming Language :: Python :: 3
Classifier: Operating System :: POSIX :: Linux
Requires-Python: >=3
Requires-Dist: PySide2>=5.10
Requires-Dist: requests>=2
Requires-Dist: importlib_resources; python_version < "3.8.5"
Dynamic: author
Dynamic: classifier
Dynamic: description
Dynamic: description-content-type
Dynamic: provides-extra
Dynamic: requires-dist
Dynamic: requires-python
Dynamic: summary
